easycom/__init__.py
easycom/device_config.py
easycom/devices.py
easycom/serial_device.py
easycom/utils.py
easycom-1.0.1.dist-info/licenses/LICENSE
easycom-1.0.1.dist-info/METADATA
easycom-1.0.1.dist-info/WHEEL
easycom-1.0.1.dist-info/top_level.txt
easycom-1.0.1.dist-info/RECORD
