Metadata-Version: 2.4
Name: easycom
Version: 1.0.1
Summary: A simple library for asynchronous serial communication
Author-email: Acemetrics Technologies <vishnu@acemetrics.com>
License: MIT License
Project-URL: Documentation, https://gitlab.com/acemetrics-technologies/easycom#README
Project-URL: Source, https://gitlab.com/acemetrics-technologies/easycom
Project-URL: Tracker, https://gitlab.com/acemetrics-technologies/easycom/-/issues
Keywords: serial,communication,arduino,pico,teensy,embedded
Classifier: Programming Language :: Python :: 3
Classifier: License :: OSI Approved :: MIT License
Classifier: Operating System :: OS Independent
License-File: LICENSE
Requires-Dist: pyserial
Dynamic: license-file
